Metadata-Version: 1.1
Name: NNSAtool
Version: 0.0.5
Summary: Neural Network Semantic Analysis tool
Home-page: UNKNOWN
Author: Dmitry Paniavin
Author-email: pndmev@gmail.com
License: MIT
Keywords: Neural Network Semantic Analysis
Platform: UNKNOWN
Classifier: Development Status :: 5 - Production/Stable
Classifier: Intended Audience :: Education
Classifier: Operating System :: Microsoft :: Windows :: Windows 10
Classifier: License :: OSI Approved :: MIT License
Classifier: Programming Language :: Python :: 3
